fitbit_to_sqlite/__init__.py
fitbit_to_sqlite/cli.py
fitbit_to_sqlite/utils.py
fitbit_to_sqlite-0.6.dist-info/LICENSE
fitbit_to_sqlite-0.6.dist-info/METADATA
fitbit_to_sqlite-0.6.dist-info/WHEEL
fitbit_to_sqlite-0.6.dist-info/entry_points.txt
fitbit_to_sqlite-0.6.dist-info/top_level.txt
fitbit_to_sqlite-0.6.dist-info/RECORD
