Metadata-Version: 2.1
Name: fitbit-to-sqlite
Version: 0.6
Summary: Save data from Fitbit Takeout to an SQLite database
Home-page: https://github.com/mrphil007/fitbit-to-sqlite
Author: Phil Rossiter
License: Apache License, Version 2.0
Platform: UNKNOWN
Requires-Dist: sqlite-utils (>=2.7.2)
Requires-Dist: click
Provides-Extra: test
Requires-Dist: pytest ; extra == 'test'
